Calculadora/Binario-BCD/CONTROL_BBCD.v
  module CONTROL_BBCD(
    input CLK,
    input MSB,
    input Z,
    input INIT,

    output reg LD,
    output reg DEC,
    output reg SH,
    output reg ADD3,
    output reg DONE
  );    
    
  // DEFINICIÓN DE ESTADOS
    parameter S_START     = 3'b000;
    parameter S_SUM       = 3'b001;
    parameter S_SHIFT_DEC = 3'b010;
    parameter S_CHECK     = 3'b011;
    parameter S_END1      = 3'b100;
    
    reg [2:0] STATE, NEXT_STATE;

    // MAQUINA DE ESTADOS - REGISTRO DE ESTADO
always @(posedge CLK) begin
    STATE <= NEXT_STATE;
end

always @(*) begin

  case (STATE)
  
    S_START: begin
      if (INIT)  NEXT_STATE = S_SUM;
      else       NEXT_STATE = S_START;
    end

    S_SUM: begin
    NEXT_STATE = S_SHIFT_DEC;
    end

    S_SHIFT_DEC: begin
      NEXT_STATE = S_CHECK;
    end

    S_CHECK: begin
        if (Z)                    NEXT_STATE = S_END1;
        else if (!MSB && !Z)      NEXT_STATE = S_SHIFT_DEC;
        else if (MSB && !Z)       NEXT_STATE = S_SUM;
        else                      NEXT_STATE = S_CHECK;
    end

    S_END1: begin
      NEXT_STATE = S_END1; // estado final
    end

    default: NEXT_STATE = S_START;
  endcase
end

    // LÓGICA DE SALIDAS (según diagrama)
    always @(*) begin
      case (STATE)

        S_START: begin
          DONE = 0;
          SH   = 0;
          DEC  = 0;
          LD   = 1;
          ADD3 = 0;
        end

        S_SUM: begin
          DONE = 0;
          SH   = 0;
          DEC  = 0;
          LD   = 0;
          ADD3 = 1; 
        end

        S_SHIFT_DEC: begin
          DONE = 0;
          SH   = 1;
          DEC  = 1;
          LD   = 0;
          ADD3 = 0;
        end

        S_CHECK: begin
          DONE = 0;
          SH   = 0;
          DEC  = 0;
          LD   = 0;
          ADD3 = 0;
        end

        S_END1: begin
          DONE = 1;
          SH   = 0;
          DEC  = 0;
          LD   = 0;
          ADD3 = 0;
        end

        default: begin
          DONE = 0;
          SH   = 0;
          LD   = 0;
          DEC  = 0;
          ADD3 = 0;
        end

      endcase
    end

endmodule

Calculadora/rtl/cores/binario-BCD/LSR_BBCD.v
module LSR_BBCD (
    input CLK,
    input SH,
    input LD,

    input  [15:0] Op_A_in,    // valor binario de entrada 

 // Entradas desde los sumadores (nuevos valores de cada nibble)
    input  [3:0] UNITN,
    input  [3:0] DECN,
    input  [3:0] CENTN,
    input  [3:0] MILN,

  // Salidas: nibbles actuales de A
    output [3:0]UNIT,
    output [3:0]DEC,
    output [3:0]CENT,
    output [3:0]MIL
    

);  
    reg [15:0] A;
    reg [15:0] Op_A;
    
    assign UNIT = A[3:0];     // bits 3 a 0
    assign DEC  = A[7:4];     // bits 7 a 4
    assign CENT = A[11:8];    // bits 11 a 8
    assign MIL  = A[15:12];   // bits 15 a 12

    always @(posedge CLK) begin
      if (LD) begin
            // Inicializa los registros
            A    <= 16'd0;
            Op_A <= Op_A_in;
        end
        
        else begin
            if (SH) begin
                {A, Op_A} <= {A, Op_A} << 1;
            end
            else begin
                A[3:0]   <= UNITN;
                A[7:4]   <= DECN;
                A[11:8]  <= CENTN;
                A[15:12] <= MILN;
            end
        end
    end

endmodule

Calculadora/rtl/cores/binario-BCD/CONTADOR_BBCD.v
module CONTADOR_BBCD (
    input CLK,
    input LD,      // Señal para cargar el valor inicial (16)
    input DEC,     // Habilitación de decremento
    output reg Z   // Bandera: 1 cuando el contador llega a 0
);

    reg [4:0] count;

always @(posedge CLK) begin
    if (LD) begin
        count <= 5'd16;
        Z <= 0;   // <-- limpiar bandera al cargar
    end
    else if (DEC && count != 0)
        count <= count - 1;

    // Bandera cuando count llega a 0
    else if (count == 0)
        Z <= 1;
end


endmodule

Calculadora/rtl/cores/binario-BCD/SUM_C2_BBCD.v
module SUM_C2_BBCD (
        input ADD3, 
        input [3:0]UNIT,
        input [3:0]DEC,
        input [3:0]CENT,
        input [3:0]MIL,

        output reg [3:0] UNITN,
        output reg [3:0] DECN,
        output reg [3:0] CENTN,
        output reg [3:0] MILN,
        output MSB
);
// Registros intermedios de 5 bits 
    reg [4:0] diffU;
    reg [4:0] diffD;
    reg [4:0] diffC;
    reg [4:0] diffM;

   always @(*) begin
        // Resta en complemento a dos 
        diffU = {1'b0, UNIT} + 5'b11011;  // -5 = 5'b11011
        diffD = {1'b0, DEC}  + 5'b11011;
        diffC = {1'b0, CENT} + 5'b11011;
        diffM = {1'b0, MIL}  + 5'b11011;

     // Por defecto, salida sin sumar +3
        UNITN = UNIT;
        DECN  = DEC;
        CENTN = CENT;
        MILN  = MIL;

        // Si la resta no es negativa (MSB=0), sumar 3
        if (ADD3 && diffU[4] == 1'b0) UNITN = UNIT + 4'd3;
        if (ADD3 && diffD[4] == 1'b0) DECN  = DEC  + 4'd3;
        if (ADD3 && diffC[4] == 1'b0) CENTN = CENT + 4'd3;
        if (ADD3 && diffM[4] == 1'b0) MILN  = MIL  + 4'd3;
    end

   // MSB = 1 si AL MENOS UN nibble necesita suma
    assign MSB = (!diffU[4] || !diffD[4] || !diffC[4] || !diffM[4]);

endmodule

Calculadora/rtl/cores/binario-BCD/Binario-BCD.v
module BinarioABCD(
input CLK,
input [15:0] Op_A, //numero binario entrada
input INIT,

output [3:0] UNIT,
output [3:0] DEC,
output [3:0] CENT,
output [3:0] MIL,
output DONE

);

// Señales internas
        wire W_MSB; 
        wire W_Z;
        wire W_LD;
        wire W_DEC;
        wire W_SH;
        wire W_ADD3;
        
        wire [3:0] W_UNITN;
        wire [3:0] W_DECN;
        wire [3:0] W_CENTN;
        wire [3:0] W_MILN;

SUM_C2_BBCD SUM_C2_BBCD0(
        .ADD3(W_ADD3),
        .UNIT(UNIT),
        .DEC(DEC),
        .CENT(CENT),
        .MIL(MIL),

        .UNITN(W_UNITN),
        .DECN(W_DECN),
        .CENTN(W_CENTN),
        .MILN(W_MILN),
        .MSB(W_MSB)        
);

CONTADOR_BBCD CONTADOR_BBCD0 (
        .CLK(CLK),
        .LD(W_LD),
        .DEC(W_DEC),
        .Z(W_Z)
);

LSR_BBCD LSR_BBCD0(
        .CLK(CLK),
        .SH(W_SH),
        .LD(W_LD),

        .Op_A_in(Op_A),

        .UNITN(W_UNITN),
        .DECN(W_DECN),
        .CENTN(W_CENTN),
        .MILN(W_MILN),   

        .UNIT(UNIT),
        .DEC(DEC),
        .CENT(CENT),
        .MIL(MIL)
);

CONTROL_BBCD CONTROL_BBCD0 (
        .CLK(CLK),
        .MSB(W_MSB),
        .Z(W_Z),
        .INIT(INIT),
    
        .LD(W_LD),
        .DEC(W_DEC),
        .SH(W_SH),
        .ADD3(W_ADD3),
        .DONE(DONE)        
);

endmodule

Calculadora/rtl/cores/binario-BCD/Periferico_BBCD.v
module Periferico_BinarioABCD (
  input CLK,
  input reset,
  input [15:0] d_in,    // dato de entrada desde el bus
  input cs,             // chip select
  input [5:0] addr,     // dirección del registro 
  input rd,             // lectura
  input wr,             // escritura
  output reg [15:0] d_out // salida hacia el bus
);


  // Registros internos

  reg [3:0] s;             // Selector 
  reg [15:0] Op_A;         // Número binario de entrada
  reg INIT;                // Señal de inicio

  wire [3:0] UNIT;
  wire [3:0] DEC;
  wire [3:0] CENT;
  wire [3:0] MIL;
  wire DONE;

  wire [15:0] RESULT;
  assign RESULT = {MIL, CENT, DEC, UNIT};
  // 1. Decodificador de direcciones

  always @(*) begin
    if (cs) begin
      case (addr)
        6'h04: s = 4'b0001; // Op_A
        6'h08: s = 4'b0010; // INIT
        6'h0C: s = 4'b0100; // RESULT
        6'h10: s = 4'b1000; // DONE 
        default: s = 4'b0000;
      endcase
    end else
      s = 4'b0000;
  end

  // 2. Escritura de registros

  always @(posedge CLK) begin
    if (reset) begin
      Op_A <= 0;
      INIT <= 0;
    end
    else begin
      if (cs && wr) begin
		   Op_A <= s[0] ? d_in    : Op_A;	//Write Registers
		   INIT <= s[1] ? d_in[0] : INIT;
      end
    end
  end

  // 3. Lectura de registros

  always @(posedge CLK) begin
    if (reset)
      d_out <= 0;
    else if (cs && rd) begin
      case (s[3:0])
        4'b0100: d_out <= RESULT;   
        4'b1000: d_out <= {15'b0, DONE};     
        default: d_out <= 16'b0;
      endcase
    end
  end

  // 4. Instancia del módulo BinarioABCD

  BinarioABCD u_BinarioABCD (
    .CLK(CLK),
    .Op_A(Op_A),
    .INIT(INIT),
    .UNIT(UNIT),
    .DEC(DEC),
    .CENT(CENT),
    .MIL(MIL),
    .DONE(DONE)
  );

endmodule

Calculadora/rtl/cores/binario-BCD/testbench.v
`timescale 1ns/1ps

module tb_Periferico_BinarioABCD;

  // ==========================
  // Entradas principales
  // ==========================
  reg CLK;
  reg reset;
  reg cs;
  reg rd;
  reg wr;
  reg [5:0] addr;
  reg [15:0] d_in;

  // ==========================
  // Salidas
  // ==========================
  wire [15:0] d_out;

  // ==========================
  // Instancia del periférico
  // ==========================
  Periferico_BinarioABCD uut (
    .CLK(CLK),
    .reset(reset),
    .d_in(d_in),
    .cs(cs),
    .addr(addr),
    .rd(rd),
    .wr(wr),
    .d_out(d_out)
  );

  // ==========================
  // Señales internas para debug
  // ==========================
  wire [15:0] OpA_int   = uut.Op_A;
  wire INIT_int         = uut.INIT;
  wire [3:0] UNIT_int   = uut.UNIT;
  wire [3:0] DEC_int    = uut.DEC;
  wire [3:0] CENT_int   = uut.CENT;
  wire [3:0] MIL_int    = uut.MIL;
  wire DONE_int         = uut.DONE;

  // ==========================
  // Generador de reloj
  // ==========================
  initial begin
    CLK = 0;
    forever #5 CLK = ~CLK; // 10ns periodo
  end

  // ==========================
  // Tareas de lectura y escritura
  // ==========================
  task write_reg(input [5:0] address, input [15:0] data);
    begin
      @(posedge CLK);
      cs   = 1;
      wr   = 1;
      rd   = 0;
      addr = address;
      d_in = data;
      @(posedge CLK);
      cs   = 0;
      wr   = 0;
      d_in = 0;
      $display("[%0t] WRITE addr=0x%0h data=%0d (0x%0h)", $time, address, data, data);
    end
  endtask

  task read_reg(input [5:0] address);
    begin
      @(posedge CLK);
      cs   = 1;
      rd   = 1;
      wr   = 0;
      addr = address;
      @(posedge CLK);
      cs   = 0;
      rd   = 0;
    end
  endtask

 
  initial begin
    $dumpfile("tb_Periferico_BinarioABCD.vcd");
    $dumpvars(0, tb_Periferico_BinarioABCD);

  end

  // ==========================
  // Secuencia principal
  // ==========================
  integer i;

  initial begin
    reset = 1;
    cs = 0; wr = 0; rd = 0;
    addr = 0; d_in = 0;
    #20 reset = 0;

    $display("\n Prueba de conversión BIN->BCD\n");

    // Escribir valor binario (ejemplo: 1234 decimal)
    write_reg(6'h04, 16'd1234); // Op_A
    write_reg(6'h08, 16'd1);    // INIT

    // Esperar hasta que DONE sea 1
    for (i = 0; i < 500; i = i + 1) begin
      @(posedge CLK);
      if (DONE_int) begin
        $display("\n DONE detectado en t=%0t", $time);
        i = 500;
      end
    end

    // Leer resultados
    read_reg(6'h0C); // UNIT
    read_reg(6'h10); // DEC
    read_reg(6'h14); // CENT
    read_reg(6'h18); // MIL
    read_reg(6'h1C); // DONE

    $display("\n[RESULTADO FINAL]");
    $display("BIN = %0d (0x%0h)", OpA_int, OpA_int);
    $display("BCD = %1d%1d%1d%1d", MIL_int, CENT_int, DEC_int, UNIT_int);

    #50;
    $display("\n=== FIN DE SIMULACIÓN ===");
    $finish;
  end

endmodule

/*
 si se quiere simular, pegar esto en consola: 
 iverilog -o sim Binario-BCD.v CONTADOR_BBCD.v CONTROL_BBCD.v LSR_BBCD.v Periferico_BBCD.v SUM_C2_BBCD.v testbench.v
 vvp sim
*/

Calculadora/rtl/cores/binario-BCD/tb_Periferico_BinarioABCD.vcd
$date
	Mon Nov 24 18:27:14 2025
$end
$version
	Icarus Verilog
$end
$timescale
	1ps
$end
$scope module tb_Periferico_BinarioABCD $end
$var wire 4 ! CENT_int [3:0] $end
$var wire 4 " DEC_int [3:0] $end
$var wire 1 # DONE_int $end
$var wire 1 $ INIT_int $end
$var wire 4 % MIL_int [3:0] $end
$var wire 16 & OpA_int [15:0] $end
$var wire 4 ' UNIT_int [3:0] $end
$var wire 16 ( d_out [15:0] $end
$var reg 1 ) CLK $end
$var reg 6 * addr [5:0] $end
$var reg 1 + cs $end
$var reg 16 , d_in [15:0] $end
$var reg 1 - rd $end
$var reg 1 . reset $end
$var reg 1 / wr $end
$var integer 32 0 i [31:0] $end
$scope module uut $end
$var wire 1 ) CLK $end
$var wire 6 1 addr [5:0] $end
$var wire 1 + cs $end
$var wire 16 2 d_in [15:0] $end
$var wire 1 - rd $end
$var wire 1 . reset $end
$var wire 1 / wr $end
$var wire 4 3 UNIT [3:0] $end
$var wire 16 4 RESULT [15:0] $end
$var wire 4 5 MIL [3:0] $end
$var wire 1 6 DONE $end
$var wire 4 7 DEC [3:0] $end
$var wire 4 8 CENT [3:0] $end
$var reg 1 9 INIT $end
$var reg 16 : Op_A [15:0] $end
$var reg 16 ; d_out [15:0] $end
$var reg 4 < s [3:0] $end
$scope module u_BinarioABCD $end
$var wire 1 ) CLK $end
$var wire 1 9 INIT $end
$var wire 16 = Op_A [15:0] $end
$var wire 1 > W_Z $end
$var wire 4 ? W_UNITN [3:0] $end
$var wire 1 @ W_SH $end
$var wire 1 A W_MSB $end
$var wire 4 B W_MILN [3:0] $end
$var wire 1 C W_LD $end
$var wire 4 D W_DECN [3:0] $end
$var wire 1 E W_DEC $end
$var wire 4 F W_CENTN [3:0] $end
$var wire 1 G W_ADD3 $end
$var wire 4 H UNIT [3:0] $end
$var wire 4 I MIL [3:0] $end
$var wire 1 6 DONE $end
$var wire 4 J DEC [3:0] $end
$var wire 4 K CENT [3:0] $end
$scope module CONTADOR_BBCD0 $end
$var wire 1 ) CLK $end
$var wire 1 C LD $end
$var wire 1 E DEC $end
$var reg 1 > Z $end
$var reg 5 L count [4:0] $end
$upscope $end
$scope module CONTROL_BBCD0 $end
$var wire 1 ) CLK $end
$var wire 1 9 INIT $end
$var wire 1 > Z $end
$var wire 1 A MSB $end
$var parameter 3 M S_CHECK $end
$var parameter 3 N S_END1 $end
$var parameter 3 O S_SHIFT_DEC $end
$var parameter 3 P S_START $end
$var parameter 3 Q S_SUM $end
$var reg 1 G ADD3 $end
$var reg 1 E DEC $end
$var reg 1 6 DONE $end
$var reg 1 C LD $end
$var reg 3 R NEXT_STATE [2:0] $end
$var reg 1 @ SH $end
$var reg 3 S STATE [2:0] $end
$upscope $end
$scope module LSR_BBCD0 $end
$var wire 1 ) CLK $end
$var wire 1 C LD $end
$var wire 16 T Op_A_in [15:0] $end
$var wire 1 @ SH $end
$var wire 4 U UNITN [3:0] $end
$var wire 4 V UNIT [3:0] $end
$var wire 4 W MILN [3:0] $end
$var wire 4 X MIL [3:0] $end
$var wire 4 Y DECN [3:0] $end
$var wire 4 Z DEC [3:0] $end
$var wire 4 [ CENTN [3:0] $end
$var wire 4 \ CENT [3:0] $end
$var reg 16 ] A [15:0] $end
$var reg 16 ^ Op_A [15:0] $end
$upscope $end
$scope module SUM_C2_BBCD0 $end
$var wire 1 G ADD3 $end
$var wire 4 _ CENT [3:0] $end
$var wire 4 ` DEC [3:0] $end
$var wire 4 a MIL [3:0] $end
$var wire 1 A MSB $end
$var wire 4 b UNIT [3:0] $end
$var reg 4 c CENTN [3:0] $end
$var reg 4 d DECN [3:0] $end
$var reg 4 e MILN [3:0] $end
$var reg 4 f UNITN [3:0] $end
$var reg 5 g diffC [4:0] $end
$var reg 5 h diffD [4:0] $end
$var reg 5 i diffM [4:0] $end
$var reg 5 j diffU [4:0] $end
$upscope $end
$upscope $end
$upscope $end
$scope task read_reg $end
$var reg 6 k address [5:0] $end
$upscope $end
$scope task write_reg $end
$var reg 6 l address [5:0] $end
$var reg 16 m data [15:0] $end
$upscope $end
$upscope $end
$enddefinitions $end
$comment Show the parameter values. $end
$dumpall
b1 Q
b0 P
b10 O
b100 N
b11 M
$end
#0
$dumpvars
bx m
bx l
bx k
bx j
bx i
bx h
bx g
bx f
bx e
bx d
bx c
bx b
bx a
bx `
bx _
bx ^
bx ]
bx \
bx [
bx Z
bx Y
bx X
bx W
bx V
bx U
bx T
bx S
bx R
bx L
bx K
bx J
bx I
bx H
xG
bx F
xE
bx D
xC
bx B
xA
x@
bx ?
x>
bx =
b0 <
bx ;
bx :
x9
bx 8
bx 7
x6
bx 5
bx 4
bx 3
b0 2
b0 1
bx 0
0/
1.
0-
b0 ,
0+
b0 *
0)
bx (
bx '
bx &
bx %
x$
x#
bx "
bx !
$end
#5000
b0 R
0$
09
b0 &
b0 :
b0 =
b0 T
b0 (
b0 ;
1)
#10000
0)
#15000
0G
1C
0E
0@
0#
06
b0 S
1)
#20000
0)
b10011010010 m
b100 l
0.
#25000
0A
b0 B
b0 W
b0 e
b0 F
b0 [
b0 c
b0 D
b0 Y
b0 d
b0 ?
b0 U
b0 f
b11011 i
b11011 g
b11011 h
b11011 j
b0 '
b0 3
b0 H
b0 V
b0 b
b0 "
b0 7
b0 J
b0 Z
b0 `
b0 !
b0 8
b0 K
b0 \
b0 _
b0 4
b0 %
b0 5
b0 I
b0 X
b0 a
0>
b1111 L
b0 ^
b0 ]
b1 <
b10011010010 ,
b10011010010 2
b100 *
b100 1
1/
1+
1)
#30000
0)
#35000
b10011010010 &
b10011010010 :
b10011010010 =
b10011010010 T
b0 <
b1 m
b1000 l
b0 ,
b0 2
0/
0+
1)
#40000
0)
#45000
b10011010010 ^
b10 <
b1 ,
b1 2
b1000 *
b1000 1
1/
1+
1)
#50000
0)
#55000
b1 R
1$
19
b0 <
b0 0
b0 ,
b0 2
0/
0+
1)
#60000
0)
#65000
1G
0C
b10 R
b1 S
b1 0
1)
#70000
0)
#75000
0G
1E
1@
b11 R
b10 S
b10 0
1)
#80000
0)
#85000
0E
0@
b10 R
b1110 L
b100110100100 ^
b11 S
b11 0
1)
#90000
0)
#95000
1E
1@
b11 R
b10 S
b100 0
1)
#100000
0)
#105000
0E
0@
b10 R
b1101 L
b1001101001000 ^
b11 S
b101 0
1)
#110000
0)
#115000
1E
1@
b11 R
b10 S
b110 0
1)
#120000
0)
#125000
0E
0@
b10 R
b1100 L
b10011010010000 ^
b11 S
b111 0
1)
#130000
0)
#135000
1E
1@
b11 R
b10 S
b1000 0
1)
#140000
0)
#145000
0E
0@
b10 R
b1011 L
b100110100100000 ^
b11 S
b1001 0
1)
#150000
0)
#155000
1E
1@
b11 R
b10 S
b1010 0
1)
#160000
0)
#165000
0E
0@
b10 R
b1010 L
b1001101001000000 ^
b11 S
b1011 0
1)
#170000
0)
#175000
1E
1@
b11 R
b10 S
b1100 0
1)
#180000
0)
#185000
b1 ?
b1 U
b1 f
b11100 j
b1 4
b1 '
b1 3
b1 H
b1 V
b1 b
0E
0@
b10 R
b1001 L
b1 ]
b11010010000000 ^
b11 S
b1101 0
1)
#190000
0)
#195000
1E
1@
b11 R
b10 S
b1110 0
1)
#200000
0)
#205000
b10 ?
b10 U
b10 f
b11101 j
b10 4
b10 '
b10 3
b10 H
b10 V
b10 b
0E
0@
b10 R
b1000 L
b10 ]
b110100100000000 ^
b11 S
b1111 0
1)
#210000
0)
#215000
1E
1@
b11 R
b10 S
b10000 0
1)
#220000
0)
#225000
b100 ?
b100 U
b100 f
b11111 j
b100 4
b100 '
b100 3
b100 H
b100 V
b100 b
0E
0@
b10 R
b111 L
b100 ]
b1101001000000000 ^
b11 S
b10001 0
1)
#230000
0)
#235000
1E
1@
b11 R
b10 S
b10010 0
1)
#240000
0)
#245000
1A
b1001 ?
b1001 U
b1001 f
b100 j
b1001 4
b1001 '
b1001 3
b1001 H
b1001 V
b1001 b
0E
0@
b1 R
b110 L
b1001 ]
b1010010000000000 ^
b11 S
b10011 0
1)
#250000
0)
#255000
b1100 ?
b1100 U
b1100 f
1G
b10 R
b1 S
b10100 0
1)
#260000
0)
#265000
b111 j
b1100 4
b1100 '
b1100 3
b1100 H
b1100 V
b1100 b
0G
1E
1@
b11 R
b1100 ]
b10 S
b10101 0
1)
#270000
0)
#275000
b1 D
b1 Y
b1 d
b1001 ?
b1001 U
b1001 f
b11100 h
b100 j
0E
0@
b1 R
b1001 '
b1001 3
b1001 H
b1001 V
b1001 b
b11001 4
b1 "
b1 7
b1 J
b1 Z
b1 `
b11 S
b11001 ]
b100100000000000 ^
b101 L
b10110 0
1)
#280000
0)
#285000
b1100 ?
b1100 U
b1100 f
1G
b10 R
b1 S
b10111 0
1)
#290000
0)
#295000
b111 j
0G
1E
1@
b11 R
b11100 4
b1100 '
b1100 3
b1100 H
b1100 V
b1100 b
b10 S
b11100 ]
b11000 0
1)
#300000
0)
#305000
b11 D
b11 Y
b11 d
b1000 ?
b1000 U
b1000 f
b11110 h
b11 j
b1000 '
b1000 3
b1000 H
b1000 V
b1000 b
b111000 4
b11 "
b11 7
b11 J
b11 Z
b11 `
0E
0@
b1 R
b100 L
b111000 ]
b1001000000000000 ^
b11 S
b11001 0
1)
#310000
0)
#315000
b1011 ?
b1011 U
b1011 f
1G
b10 R
b1 S
b11010 0
1)
#320000
0)
#325000
b110 j
b111011 4
b1011 '
b1011 3
b1011 H
b1011 V
b1011 b
0G
1E
1@
b11 R
b111011 ]
b10 S
b11011 0
1)
#330000
0)
#335000
b111 D
b111 Y
b111 d
b111 ?
b111 U
b111 f
b10 h
b10 j
0E
0@
b1 R
b111 '
b111 3
b111 H
b111 V
b111 b
b1110111 4
b111 "
b111 7
b111 J
b111 Z
b111 `
b11 S
b1110111 ]
b10000000000000 ^
b11 L
b11100 0
1)
#340000
0)
#345000
b1010 D
b1010 Y
b1010 d
b1010 ?
b1010 U
b1010 f
1G
b10 R
b1 S
b11101 0
1)
#350000
0)
#355000
b101 h
b101 j
0G
1E
1@
b11 R
b1010 "
b1010 7
b1010 J
b1010 Z
b1010 `
b10101010 4
b1010 '
b1010 3
b1010 H
b1010 V
b1010 b
b10 S
b10101010 ]
b11110 0
1)
#360000
0)
#365000
b1 F
b1 [
b1 c
b101 D
b101 Y
b101 d
b100 ?
b100 U
b100 f
b11100 g
b0 h
b11111 j
b100 '
b100 3
b100 H
b100 V
b100 b
b101 "
b101 7
b101 J
b101 Z
b101 `
b101010100 4
b1 !
b1 8
b1 K
b1 \
b1 _
0E
0@
b1 R
b10 L
b101010100 ]
b100000000000000 ^
b11 S
b11111 0
1)
#370000
0)
#375000
b1000 D
b1000 Y
b1000 d
1G
b10 R
b1 S
b100000 0
1)
#380000
0)
#385000
b11 h
b110000100 4
b1000 "
b1000 7
b1000 J
b1000 Z
b1000 `
0G
1E
1@
b11 R
b110000100 ]
b10 S
b100001 0
1)
#390000
0)
#395000
b11 F
b11 [
b11 c
b0 D
b0 Y
b0 d
b1000 ?
b1000 U
b1000 f
b11110 g
b11011 h
b11 j
0E
0@
b1 R
b1000 '
b1000 3
b1000 H
b1000 V
b1000 b
b0 "
b0 7
b0 J
b0 Z
b0 `
b1100001000 4
b11 !
b11 8
b11 K
b11 \
b11 _
b11 S
b1100001000 ]
b1000000000000000 ^
b1 L
b100010 0
1)
#400000
0)
#405000
b1011 ?
b1011 U
b1011 f
1G
b10 R
b1 S
b100011 0
1)
#410000
0)
#415000
b110 j
0G
1E
1@
b11 R
b1100001011 4
b1011 '
b1011 3
b1011 H
b1011 V
b1011 b
b10 S
b1100001011 ]
b100100 0
1)
#420000
0)
#425000
b110 F
b110 [
b110 c
b1 D
b1 Y
b1 d
b111 ?
b111 U
b111 f
b1 g
b11100 h
b10 j
b111 '
b111 3
b111 H
b111 V
b111 b
b1 "
b1 7
b1 J
b1 Z
b1 `
b11000010111 4
b110 !
b110 8
b110 K
b110 \
b110 _
0E
0@
b1 R
b0 L
b11000010111 ]
b0 ^
b11 S
b100101 0
1)
#430000
0)
#435000
b1001 F
b1001 [
b1001 c
b1010 ?
b1010 U
b1010 f
1G
b10 R
b1 S
1>
b100110 0
1)
#440000
0)
#445000
b100 g
b101 j
b1001 !
b1001 8
b1001 K
b1001 \
b1001 _
b100100011010 4
b1010 '
b1010 3
b1010 H
b1010 V
b1010 b
0G
1E
1@
b11 R
b100100011010 ]
b10 S
b100111 0
1)
#450000
0)
#455000
0A
b1 B
b1 W
b1 e
b10 F
b10 [
b10 c
b11 D
b11 Y
b11 d
b100 ?
b100 U
b100 f
b11100 i
b11101 g
b11110 h
b11111 j
0E
0@
b100 R
b100 '
b100 3
b100 H
b100 V
b100 b
b11 "
b11 7
b11 J
b11 Z
b11 `
b10 !
b10 8
b10 K
b10 \
b10 _
b1001000110100 4
b1 %
b1 5
b1 I
b1 X
b1 a
b11 S
b1001000110100 ]
b101000 0
1)
#460000
0)
#465000
1#
16
b100 S
b101001 0
1)
#470000
0)
#475000
b1100 k
b111110101 0
1)
#480000
0)
#485000
b100 <
b1100 *
b1100 1
1-
1+
1)
#490000
0)
#495000
b1001000110100 (
b1001000110100 ;
b0 <
b10000 k
0-
0+
1)
#500000
0)
#505000
b0 (
b0 ;
b1000 <
b10000 *
b10000 1
1-
1+
1)
#510000
0)
#515000
b1 (
b1 ;
b0 <
b10100 k
0-
0+
1)
#520000
0)
#525000
b0 (
b0 ;
b10100 *
b10100 1
1-
1+
1)
#530000
0)
#535000
b11000 k
0-
0+
1)
#540000
0)
#545000
b11000 *
b11000 1
1-
1+
1)
#550000
0)
#555000
b11100 k
0-
0+
1)
#560000
0)
#565000
b11100 *
b11100 1
1-
1+
1)
#570000
0)
#575000
0-
0+
1)
