Calculadora/Multiplicador/control_mult.v
module control_mult(clk , rst, lsb_B, init , z, done , sh ,reset , add);
    input clk;
    input rst;
    input lsb_B;
    input init;
    input z;

    output reg done;
    output reg sh;
    output reg reset;
    output reg add;

    parameter START = 3'b000;
    parameter CHECK = 3'b001;
    parameter SHIFT = 3'b010;
    parameter ADD   = 3'b011;
    parameter fin   = 3'b100;

    reg [2:0] state;
    reg [3:0] count;

    initial begin
        done = 0;
        sh = 0;
        reset = 0;
        add = 0;
        state = 0;
    end

    always @(posedge clk) begin
        if (rst) begin
            state = START;
            count = 0;
        end
        else begin
            case(state)
                START: begin
                    count = 0;
                    if(init)
                        state = CHECK;
                    else
                        state = START;
                end

                CHECK: begin
                    if(lsb_B)
                        state = ADD;
                    else
                        state = SHIFT;
                end

                SHIFT: begin
                    if(z)
                        state = fin;
                    else
                        state = CHECK;
                end

                ADD: begin
                    state = SHIFT;
                end

                fin: begin
                    count = count + 1;
                    if(count > 9)
                        state = START;
                    else
                        state = fin;
                end

                default: state = START;
            endcase
        end
    end

    always @(state) begin
        case(state)
            START: begin
                done = 0;
                sh   = 0;
                reset = 1;
                add  = 0;
            end

            CHECK: begin
                done = 0;
                sh   = 0;
                reset = 0;
                add  = 0;
            end

            SHIFT: begin
                done = 0;
                sh   = 1;
                reset = 0;
                add  = 0;
            end

            ADD: begin
                done = 0;
                sh   = 0;
                reset = 0;
                add  = 1;
            end

            fin: begin
                done = 1;
                sh   = 0;
                reset = 0;
                add  = 0;
            end

            default: begin
                done = 0;
                sh   = 0;
                reset = 0;
                add  = 0;
            end
        endcase
    end
endmodule

Calculadora/rtl/cores/multiplicador/acc.v
module acc (clk , A, add, rst,
pp);
    input clk;
    input [31:0] A;
    input add;
    input rst;
    output reg [31:0] pp;

initial pp = 0;

always @(negedge clk)
    if (rst)
        pp = 32'h00000000;
    else
        begin
        if (add) pp = pp + A;
        else pp = pp;
        end
endmodule

Calculadora/rtl/cores/multiplicador/comp.v
module comp(B, z);
input [15:0]B;
output z;
reg tmp;

initial tmp = 0;
assign z = tmp;

    always@(*)
        tmp = (B==0) ? 1'b1 : 1'b0;
endmodule

Calculadora/rtl/cores/multiplicador/lsr.v
module lsr (clk , in_A , shift , load , s_A);
    input clk;
    input [15:0]in_A;
    input load;
    input shift;
    output reg [31:0]s_A;

    always @(negedge clk)
        if(load)
            s_A = in_A ;
        else
            begin
                if(shift) s_A = s_A << 1 ;
                else s_A = s_A;
            end
endmodule

Calculadora/rtl/cores/multiplicador/rsr.v
module rsr (clk, in_B , shift , load , s_B);
    input clk;
    input [15:0]in_B;
    input load;
    input shift;
    output reg [15:0]s_B;

always @(negedge clk)
    if(load)
        s_B = in_B ;
    else
        begin
            if(shift) s_B = s_B >> 1;
            else s_B = s_B;
        end
endmodule

Calculadora/rtl/cores/multiplicador/multiplicador.v
module mult_32(clk , rst , init , A , B , pp , done);
    input rst;
    input clk;
    input init;
    input [15:0]A;
    input [15:0]B;
    output [31:0]pp;
    output done;

    wire w_sh;
    wire w_reset;
    wire w_add;
    wire w_z;

    wire [31:0]w_A;
    wire [15:0] w_B;

    rsr rsr0 (.clk(clk), .in_B(B) , .shift(w_sh) , .load(w_reset) , .s_B(w_B));
    lsr lsr0 (.clk(clk), .in_A(A) , .shift(w_sh) , .load(w_reset) , .s_A(w_A));
    comp comp0(.B(w_B), .z(w_z));
    acc acc0 (.clk(clk), .A(w_A) , .add(w_add), .rst(w_reset), .pp(pp));
    control_mult control0 (.clk(clk), .rst(rst), .lsb_B(w_B[0]), .init(init), .z(w_z), .done(done),
                           .sh(w_sh) , .reset(w_reset) , .add(w_add) );
endmodule

Calculadora/Multiplicador/Periferico_multiplicador.v
module Periferico_multiplicador(
  input clk,
  input reset,
  input [15:0] d_in,   // dato que llega del procesador
  input cs,            // chip select (habilita el periférico)
  input [4:0] addr,    // dirección desde el bus
  input rd,            // señal de lectura
  input wr,            // señal de escritura
  output reg [31:0] d_out  // dato de salida hacia el procesador
);


//------------------------------------ regs and wires-------------------------------
reg [4:0] s; 	//selector mux_4  and write registers
reg [15:0] A;//---mult_32 input registers
reg [15:0] B;
reg init;
wire [31:0] pp;	//mult_32 output Regs
wire done;


//------------------------------------ regs and wires-------------------------------
always @(*) begin//------address_decoder------------------------------
if (cs) begin
  case (addr)
    5'h04: s =  5'b00001; // A 
    5'h08: s =  5'b00010; // B
    5'h0C: s =  5'b00100; // init
    5'h10: s =  5'b01000; // pp (resultado)
    5'h14: s =  5'b10000; // done
    default: s = 5'b00000;
  endcase
end
else 
  s = 5'b00000;
end//------------------address_decoder--------------------------------




always @(posedge clk) begin//-------------------- escritura de registros 

  if(reset) begin
    init = 0;
    A    = 0;
    B    = 0;
  end
  else begin
    if (cs && wr) begin
		   A    = s[0] ? d_in    : A;	//Write Registers
		   B    = s[1] ? d_in    : B;	//Write Registers
		   init = s[2] ? d_in[0] : init;
    end
  end

end//------------------------------------------- escritura de registros


always @(posedge clk) begin//-----------------------mux_4 :  multiplexa salidas del periferico
  if(reset)
    d_out = 0;
  else if (cs) begin
    case (s[4:0])
      5'b01000: d_out    =  pp;            
      5'b10000: d_out    = {31'b0, done};
    endcase
  end
end//-----------------------------------------------mux_4


mult_32 u_mult (
    .clk(clk),
    .rst(reset),
    .init(init),
    .A(A),
    .B(B),
    .pp(pp),
    .done(done)
  );
  
endmodule

Calculadora/rtl/cores/multiplicador/testbench.v
`timescale 1ns / 1ps

module tb_Periferico_multiplicador;

// Señales del testbench
reg clk;
reg reset;
reg [15:0] d_in;
reg cs;
reg [4:0] addr;
reg rd;
reg wr;
wire [31:0] d_out;

// Instancia del periférico
Periferico_multiplicador dut (
    .clk(clk),
    .reset(reset),
    .d_in(d_in),
    .cs(cs),
    .addr(addr),
    .rd(rd),
    .wr(wr),
    .d_out(d_out)
);

// Generador de reloj
initial clk = 0;
always #5 clk = ~clk;  // periodo de 10 ns -> 100 MHz

// Procedimiento de prueba
initial begin
  // Inicialización
  cs = 0; rd = 0; wr = 0;
  d_in = 0; addr = 0;
  reset = 1;
  #20;
  reset = 0;
  #10;

  // Escritura de A = 
  write_reg(5'h04, 16'd934);

  // Escritura de B = 
  write_reg(5'h08, 16'd367);

  // Escritura de init = 1
  write_reg(5'h0C, 16'd1);

  // Esperar que done = 1
  wait_done();

  // Leer resultado pp
  read_reg(5'h10);

  // Mostrar resultado esperado
  $display("Resultado esperado: %d", 934*367);
  $finish;
end

// Tareas auxiliares
task write_reg(input [4:0] address, input [15:0] value);
  begin
    @(posedge clk);
    cs = 1; wr = 1; rd = 0;
    addr = address;
    d_in = value;
    @(posedge clk);
    cs = 0; wr = 0;
    d_in = 0;
  end
endtask

task read_reg(input [4:0] address);
  begin
    @(posedge clk);
    cs = 1; rd = 1; wr = 0;
    addr = address;
    @(posedge clk);
    $display("Lectura addr %h -> d_out = %d", address, d_out);
    cs = 0; rd = 0;
  end
endtask

task wait_done();
  begin
    repeat (100) begin
      read_reg(5'h14);
      if (d_out[0] == 1'b1) begin
        $display("DONE recibido en tiempo %t", $time);
        disable wait_done;
      end
      #10;
    end
    $display("ERROR: no se recibió DONE");
  end
endtask

endmodule

/*
 si se quiere simular, pegar esto en consola: 
 iverilog -o sim testbench.v Periferico_multiplicador.v multiplicador.v acc.v comp.v control_mult.v lsr.v rsr.v
 vvp sim
*/

Calculadora/rtl/cores/multiplicador/TB_mult.vcd
$date
	Mon Nov 24 00:18:37 2025
$end
$version
	Icarus Verilog
$end
$timescale
	1ps
$end
$scope module tb_Periferico_multiplicador $end
$var wire 32 ! d_out [31:0] $end
$var reg 5 " addr [4:0] $end
$var reg 1 # clk $end
$var reg 1 $ cs $end
$var reg 16 % d_in [15:0] $end
$var reg 1 & rd $end
$var reg 1 ' reset $end
$var reg 1 ( wr $end
$scope module dut $end
$var wire 5 ) addr [4:0] $end
$var wire 1 # clk $end
$var wire 1 $ cs $end
$var wire 16 * d_in [15:0] $end
$var wire 1 & rd $end
$var wire 1 ' reset $end
$var wire 1 ( wr $end
$var wire 32 + pp [31:0] $end
$var wire 1 , done $end
$var reg 16 - A [15:0] $end
$var reg 16 . B [15:0] $end
$var reg 32 / d_out [31:0] $end
$var reg 1 0 init $end
$var reg 5 1 s [4:0] $end
$scope module u_mult $end
$var wire 16 2 A [15:0] $end
$var wire 16 3 B [15:0] $end
$var wire 1 # clk $end
$var wire 1 0 init $end
$var wire 1 ' rst $end
$var wire 1 4 w_z $end
$var wire 1 5 w_sh $end
$var wire 1 6 w_reset $end
$var wire 1 7 w_add $end
$var wire 16 8 w_B [15:0] $end
$var wire 32 9 w_A [31:0] $end
$var wire 32 : pp [31:0] $end
$var wire 1 , done $end
$scope module acc0 $end
$var wire 1 # clk $end
$var wire 1 6 rst $end
$var wire 1 7 add $end
$var wire 32 ; A [31:0] $end
$var reg 32 < pp [31:0] $end
$upscope $end
$scope module comp0 $end
$var wire 1 4 z $end
$var wire 16 = B [15:0] $end
$var reg 1 > tmp $end
$upscope $end
$scope module control0 $end
$var wire 1 # clk $end
$var wire 1 0 init $end
$var wire 1 ? lsb_B $end
$var wire 1 ' rst $end
$var wire 1 4 z $end
$var parameter 3 @ ADD $end
$var parameter 3 A CHECK $end
$var parameter 3 B SHIFT $end
$var parameter 3 C START $end
$var parameter 3 D fin $end
$var reg 1 7 add $end
$var reg 4 E count [3:0] $end
$var reg 1 , done $end
$var reg 1 6 reset $end
$var reg 1 5 sh $end
$var reg 3 F state [2:0] $end
$upscope $end
$scope module lsr0 $end
$var wire 1 # clk $end
$var wire 16 G in_A [15:0] $end
$var wire 1 6 load $end
$var wire 1 5 shift $end
$var reg 32 H s_A [31:0] $end
$upscope $end
$scope module rsr0 $end
$var wire 1 # clk $end
$var wire 16 I in_B [15:0] $end
$var wire 1 6 load $end
$var wire 1 5 shift $end
$var reg 16 J s_B [15:0] $end
$upscope $end
$upscope $end
$upscope $end
$scope task read_reg $end
$var reg 5 K address [4:0] $end
$upscope $end
$scope task wait_done $end
$upscope $end
$scope task write_reg $end
$var reg 5 L address [4:0] $end
$var reg 16 M value [15:0] $end
$upscope $end
$upscope $end
$enddefinitions $end
$comment Show the parameter values. $end
$dumpall
b100 D
b0 C
b10 B
b1 A
b11 @
$end
#0
$dumpvars
bx M
bx L
bx K
bx J
bx I
b0xxxxxxxxxxxxxxxx H
bx G
b0 F
bx E
x?
0>
bx =
b0 <
b0xxxxxxxxxxxxxxxx ;
b0 :
b0xxxxxxxxxxxxxxxx 9
bx 8
07
16
05
04
bx 3
bx 2
b0 1
x0
bx /
bx .
bx -
0,
b0 +
b0 *
b0 )
0(
1'
0&
b0 %
0$
0#
b0 "
bx !
$end
#5000
b0 E
b0 .
b0 3
b0 I
b0 -
b0 2
b0 G
00
b0 !
b0 /
1#
#10000
0?
14
1>
b0 9
b0 ;
b0 H
b0 8
b0 =
b0 J
0#
#15000
1#
#20000
0#
0'
#25000
1#
#30000
0#
b1111111111111111 M
b100 L
#35000
b1 1
b1111111111111111 %
b1111111111111111 *
b100 "
b100 )
1(
1$
1#
#40000
0#
#45000
b0 1
b1000 L
b0 %
b0 *
0(
0$
b1111111111111111 -
b1111111111111111 2
b1111111111111111 G
1#
#50000
b1111111111111111 9
b1111111111111111 ;
b1111111111111111 H
0#
#55000
b10 1
b1111111111111111 %
b1111111111111111 *
b1000 "
b1000 )
1(
1$
1#
#60000
0#
#65000
b0 1
b1 M
b1100 L
b0 %
b0 *
0(
0$
b1111111111111111 .
b1111111111111111 3
b1111111111111111 I
1#
#70000
1?
04
0>
b1111111111111111 8
b1111111111111111 =
b1111111111111111 J
0#
#75000
b100 1
b1 %
b1 *
b1100 "
b1100 )
1(
1$
1#
#80000
0#
#85000
b0 1
06
b10100 K
b0 %
b0 *
0(
0$
b1 F
10
1#
#90000
0#
#95000
17
b10000 1
b11 F
b10100 "
b10100 )
1&
1$
1#
#100000
b1111111111111111 +
b1111111111111111 :
b1111111111111111 <
0#
#105000
b0 1
07
15
0&
0$
b10 F
1#
#110000
b11111111111111110 9
b11111111111111110 ;
b11111111111111110 H
b111111111111111 8
b111111111111111 =
b111111111111111 J
0#
#115000
05
b10000 1
b1 F
1&
1$
1#
#120000
0#
#125000
b0 1
17
0&
0$
b11 F
1#
#130000
b101111111111111101 +
b101111111111111101 :
b101111111111111101 <
0#
#135000
07
15
b10000 1
b10 F
1&
1$
1#
#140000
b11111111111111 8
b11111111111111 =
b11111111111111 J
b111111111111111100 9
b111111111111111100 ;
b111111111111111100 H
0#
#145000
b0 1
05
0&
0$
b1 F
1#
#150000
0#
#155000
17
b10000 1
b11 F
1&
1$
1#
#160000
b1101111111111111001 +
b1101111111111111001 :
b1101111111111111001 <
0#
#165000
b0 1
07
15
0&
0$
b10 F
1#
#170000
b1111111111111111000 9
b1111111111111111000 ;
b1111111111111111000 H
b1111111111111 8
b1111111111111 =
b1111111111111 J
0#
#175000
05
b10000 1
b1 F
1&
1$
1#
#180000
0#
#185000
b0 1
17
0&
0$
b11 F
1#
#190000
b11101111111111110001 +
b11101111111111110001 :
b11101111111111110001 <
0#
#195000
07
15
b10000 1
b10 F
1&
1$
1#
#200000
b111111111111 8
b111111111111 =
b111111111111 J
b11111111111111110000 9
b11111111111111110000 ;
b11111111111111110000 H
0#
#205000
b0 1
05
0&
0$
b1 F
1#
#210000
0#
#215000
17
b10000 1
b11 F
1&
1$
1#
#220000
b111101111111111100001 +
b111101111111111100001 :
b111101111111111100001 <
0#
#225000
b0 1
07
15
0&
0$
b10 F
1#
#230000
b111111111111111100000 9
b111111111111111100000 ;
b111111111111111100000 H
b11111111111 8
b11111111111 =
b11111111111 J
0#
#235000
05
b10000 1
b1 F
1&
1$
1#
#240000
0#
#245000
b0 1
17
0&
0$
b11 F
1#
#250000
b1111101111111111000001 +
b1111101111111111000001 :
b1111101111111111000001 <
0#
#255000
07
15
b10000 1
b10 F
1&
1$
1#
#260000
b1111111111 8
b1111111111 =
b1111111111 J
b1111111111111111000000 9
b1111111111111111000000 ;
b1111111111111111000000 H
0#
#265000
b0 1
05
0&
0$
b1 F
1#
#270000
0#
#275000
17
b10000 1
b11 F
1&
1$
1#
#280000
b11111101111111110000001 +
b11111101111111110000001 :
b11111101111111110000001 <
0#
#285000
b0 1
07
15
0&
0$
b10 F
1#
#290000
b11111111111111110000000 9
b11111111111111110000000 ;
b11111111111111110000000 H
b111111111 8
b111111111 =
b111111111 J
0#
#295000
05
b10000 1
b1 F
1&
1$
1#
#300000
0#
#305000
b0 1
17
0&
0$
b11 F
1#
#310000
b111111101111111100000001 +
b111111101111111100000001 :
b111111101111111100000001 <
0#
#315000
07
15
b10000 1
b10 F
1&
1$
1#
#320000
b11111111 8
b11111111 =
b11111111 J
b111111111111111100000000 9
b111111111111111100000000 ;
b111111111111111100000000 H
0#
#325000
b0 1
05
0&
0$
b1 F
1#
#330000
0#
#335000
17
b10000 1
b11 F
1&
1$
1#
#340000
b1111111101111111000000001 +
b1111111101111111000000001 :
b1111111101111111000000001 <
0#
#345000
b0 1
07
15
0&
0$
b10 F
1#
#350000
b1111111111111111000000000 9
b1111111111111111000000000 ;
b1111111111111111000000000 H
b1111111 8
b1111111 =
b1111111 J
0#
#355000
05
b10000 1
b1 F
1&
1$
1#
#360000
0#
#365000
b0 1
17
0&
0$
b11 F
1#
#370000
b11111111101111110000000001 +
b11111111101111110000000001 :
b11111111101111110000000001 <
0#
#375000
07
15
b10000 1
b10 F
1&
1$
1#
#380000
b111111 8
b111111 =
b111111 J
b11111111111111110000000000 9
b11111111111111110000000000 ;
b11111111111111110000000000 H
0#
#385000
b0 1
05
0&
0$
b1 F
1#
#390000
0#
#395000
17
b10000 1
b11 F
1&
1$
1#
#400000
b111111111101111100000000001 +
b111111111101111100000000001 :
b111111111101111100000000001 <
0#
#405000
b0 1
07
15
0&
0$
b10 F
1#
#410000
b111111111111111100000000000 9
b111111111111111100000000000 ;
b111111111111111100000000000 H
b11111 8
b11111 =
b11111 J
0#
#415000
05
b10000 1
b1 F
1&
1$
1#
#420000
0#
#425000
b0 1
17
0&
0$
b11 F
1#
#430000
b1111111111101111000000000001 +
b1111111111101111000000000001 :
b1111111111101111000000000001 <
0#
#435000
07
15
b10000 1
b10 F
1&
1$
1#
#440000
b1111 8
b1111 =
b1111 J
b1111111111111111000000000000 9
b1111111111111111000000000000 ;
b1111111111111111000000000000 H
0#
#445000
b0 1
05
0&
0$
b1 F
1#
#450000
0#
#455000
17
b10000 1
b11 F
1&
1$
1#
#460000
b11111111111101110000000000001 +
b11111111111101110000000000001 :
b11111111111101110000000000001 <
0#
#465000
b0 1
07
15
0&
0$
b10 F
1#
#470000
b11111111111111110000000000000 9
b11111111111111110000000000000 ;
b11111111111111110000000000000 H
b111 8
b111 =
b111 J
0#
#475000
05
b10000 1
b1 F
1&
1$
1#
#480000
0#
#485000
b0 1
17
0&
0$
b11 F
1#
#490000
b111111111111101100000000000001 +
b111111111111101100000000000001 :
b111111111111101100000000000001 <
0#
#495000
07
15
b10000 1
b10 F
1&
1$
1#
#500000
b11 8
b11 =
b11 J
b111111111111111100000000000000 9
b111111111111111100000000000000 ;
b111111111111111100000000000000 H
0#
#505000
b0 1
05
0&
0$
b1 F
1#
#510000
0#
#515000
17
b10000 1
b11 F
1&
1$
1#
#520000
b1111111111111101000000000000001 +
b1111111111111101000000000000001 :
b1111111111111101000000000000001 <
0#
#525000
b0 1
07
15
0&
0$
b10 F
1#
#530000
b1111111111111111000000000000000 9
b1111111111111111000000000000000 ;
b1111111111111111000000000000000 H
b1 8
b1 =
b1 J
0#
#535000
05
b10000 1
b1 F
1&
1$
1#
#540000
0#
#545000
b0 1
17
0&
0$
b11 F
1#
#550000
b11111111111111100000000000000001 +
b11111111111111100000000000000001 :
b11111111111111100000000000000001 <
0#
#555000
07
15
b10000 1
b10 F
1&
1$
1#
#560000
0?
14
1>
b0 8
b0 =
b0 J
b11111111111111110000000000000000 9
b11111111111111110000000000000000 ;
b11111111111111110000000000000000 H
0#
#565000
b0 1
05
1,
0&
0$
b100 F
1#
#570000
0#
#575000
b10000 1
b1 E
1&
1$
1#
#580000
0#
#585000
b0 1
b10000 K
0&
0$
b10 E
b1 !
b1 /
1#
#590000
0#
#595000
b1000 1
b11 E
b10000 "
b10000 )
1&
1$
1#
#600000
0#
#605000
b0 1
0&
0$
b100 E
b11111111111111100000000000000001 !
b11111111111111100000000000000001 /
1#
